cook/__init__.py
cook/__main__.py
cook/_typing.py
cook/menu.py
cook/recipe.py
cook/ninja/__init__.py
cook/ninja/syntax.py
liblaf_cook-0.1.0.dist-info/METADATA
liblaf_cook-0.1.0.dist-info/WHEEL
liblaf_cook-0.1.0.dist-info/RECORD
