Metadata-Version: 2.3
Name: liblaf-cook
Version: 0.1.0
Summary: Add your description here
Author-email: liblaf <30631553+liblaf@users.noreply.github.com>
License: MIT
Requires-Python: >=3.8
Requires-Dist: pydantic>=2.7.1
